.gitignore
LICENSE
PKG-INFO
README.md
__init__.py
__main__.py
gupy.ico
gupy.py
gupy_logo.png
pyproject.toml
python.7z
requirements.txt
gupy/LICENSE
gupy/README.md
gupy/__init__.py
gupy/__main__.py
gupy/gupy.ico
gupy/gupy.py
gupy/gupy_logo.png
gupy/pyproject.toml
gupy/python.7z
gupy/requirements.txt
gupy/target_platforms/__init__.py
gupy/target_platforms/api.py
gupy/target_platforms/base.py
gupy/target_platforms/cmdline.py
gupy/target_platforms/desktop.py
gupy/target_platforms/etl.py
gupy/target_platforms/mobile.py
gupy/target_platforms/pwa.py
gupy/target_platforms/script.py
gupy/target_platforms/website.py
target_platforms/__init__.py
target_platforms/api.py
target_platforms/base.py
target_platforms/cmdline.py
target_platforms/desktop.py
target_platforms/etl.py
target_platforms/mobile.py
target_platforms/pwa.py
target_platforms/script.py
target_platforms/website.py
gupy_framework-0.5.2.dist-info/METADATA
gupy_framework-0.5.2.dist-info/WHEEL
gupy_framework-0.5.2.dist-info/entry_points.txt
gupy_framework-0.5.2.dist-info/licenses/LICENSE
gupy_framework-0.5.2.dist-info/RECORD
